{
  "schemaVersion": 1,
  "artifactType": "official_pdf_draft_field_map_review",
  "status": "visual_review_required",
  "lifecycle": "none",
  "notices": [
    "This is a tracked draft field-map review artifact only.",
    "This is not visual approval.",
    "This is not replacement_candidate.",
    "This is not verified_replacement.",
    "This is not production ready.",
    "This is not live routed.",
    "This does not replace human visual review, filled-data visual review, source freshness review, or counsel confirmation.",
    "Do not wire this artifact to live routes."
  ],
  "jurisdictionCode": "ND",
  "jurisdictionName": "North Dakota",
  "formSlug": "north-dakota-2-motion-to-prohibit-public-access-ar41-5f1",
  "sourcePdf": "LegalEase North Dakota/2. Motion to Prohibit Public Access AR41 5f1.pdf",
  "sourcePdfRole": "blank official source PDF from local Nationwide archive",
  "sourceCandidatePacket": "tmp/review-inbox/batch-field-map-review-next-20-round-5/north-dakota-2-motion-to-prohibit-public-access-ar41-5f1/north-dakota-2-motion-to-prohibit-public-access-ar41-5f1-candidates.json",
  "batchReviewManifest": "tmp/review-inbox/batch-field-map-review-next-20-round-5/REVIEW-MANIFEST.md",
  "mappingMode": "hybrid",
  "pdfClassification": "acroform_dirty",
  "recommendedMappingMode": "hybrid",
  "generatedFrom": "batch field-map review packet candidate extraction",
  "generatedAt": "2026-06-16T02:20:32.282Z",
  "reviewInput": {
    "visualPlacementSanityReview": "passed_for_draft_mapping_only",
    "reviewerNotes": [
      "Candidate has 15 fields and 15 widgets.",
      "Confidence counts: 3 high, 2 medium, 6 low, 4 unknown.",
      "Batch visual sanity review passed only for creating this hard-blocked draft review artifact.",
      "Filled-data visual review, source freshness review, and counsel confirmation are still required before production use."
    ]
  },
  "counts": {
    "fieldCount": 15,
    "widgetCount": 15,
    "representedWidgetCount": 15,
    "confidenceCounts": {
      "high": 3,
      "medium": 2,
      "low": 6,
      "unknown": 4
    },
    "fieldTypeCounts": {
      "text": 9,
      "checkbox": 6
    },
    "widgetsByPage": {
      "1": 15
    }
  },
  "sourceInspection": {
    "pageCount": 0,
    "fileSizeBytes": 1244725,
    "acroFormFieldCount": 0,
    "duplicateAcroFormFieldNames": []
  },
  "preservedBatchWarnings": [
    "AcroForm dictionary was detected, but no field names were found by raw inspection.",
    "No page objects were detected by raw inspection."
  ],
  "preservedBatchErrors": [],
  "risks": [
    "Status remains visual_review_required; no lifecycle promotion is implied.",
    "This is not visual approval; visual placement sanity passed only for draft mapping review.",
    "This artifact is not replacement_candidate, not verified_replacement, not production ready, and not live routed.",
    "Canonical field names still need manual review because low or unknown confidence candidates remain.",
    "Batch candidate warning preserved: AcroForm dictionary was detected, but no field names were found by raw inspection.",
    "Batch candidate warning preserved: No page objects were detected by raw inspection.",
    "Draft rectangles need full filled-data visual review before any production use.",
    "Source freshness review is still required before any production use.",
    "Counsel confirmation is still required before any production use."
  ],
  "draftFieldMap": {
    "formId": "nd_north_dakota_2_motion_to_prohibit_public_access_ar41_5f1",
    "status": "visual_review_required",
    "lifecycle": "none",
    "mappingMode": "hybrid",
    "fields": {},
    "overlays": []
  },
  "candidates": [
    {
      "candidateId": "ND-2.-Motion-to-Prohibit-Public-Access-AR41-5f1-F001-W01",
      "sourceAcroFormFieldName": "County Of",
      "fieldType": "text",
      "page": 1,
      "rect": {
        "x": 124.92,
        "y": 684.36,
        "width": 161.4,
        "height": 14.4
      },
      "draftCanonicalKey": "county",
      "canonicalKeyConfidence": "medium",
      "matcherReason": "Field name references county.",
      "reviewStatus": "canonical_key_candidate_manual_review_required",
      "warnings": [
        "candidate_only",
        "visual_review_required",
        "not_verified"
      ]
    },
    {
      "candidateId": "ND-2.-Motion-to-Prohibit-Public-Access-AR41-5f1-F002-W01",
      "sourceAcroFormFieldName": "Judicial District",
      "fieldType": "text",
      "page": 1,
      "rect": {
        "x": 324,
        "y": 684.36,
        "width": 137.52,
        "height": 14.4
      },
      "draftCanonicalKey": null,
      "canonicalKeyConfidence": "unknown",
      "matcherReason": "No conservative canonical match from AcroForm name or options.",
      "reviewStatus": "manual_review_required",
      "warnings": [
        "candidate_only",
        "visual_review_required",
        "not_verified",
        "manual_mapping_required"
      ]
    },
    {
      "candidateId": "ND-2.-Motion-to-Prohibit-Public-Access-AR41-5f1-F003-W01",
      "sourceAcroFormFieldName": "Plaintiff",
      "fieldType": "text",
      "page": 1,
      "rect": {
        "x": 72,
        "y": 652.92,
        "width": 233.16,
        "height": 14.4
      },
      "draftCanonicalKey": null,
      "canonicalKeyConfidence": "unknown",
      "matcherReason": "No conservative canonical match from AcroForm name or options.",
      "reviewStatus": "manual_review_required",
      "warnings": [
        "candidate_only",
        "visual_review_required",
        "not_verified",
        "manual_mapping_required"
      ]
    },
    {
      "candidateId": "ND-2.-Motion-to-Prohibit-Public-Access-AR41-5f1-F004-W01",
      "sourceAcroFormFieldName": "Case No",
      "fieldType": "text",
      "page": 1,
      "rect": {
        "x": 405.48,
        "y": 638.28,
        "width": 125.52,
        "height": 14.4
      },
      "draftCanonicalKey": "caseNumber",
      "canonicalKeyConfidence": "high",
      "matcherReason": "Field name is an exact conservative canonical label match.",
      "reviewStatus": "canonical_key_candidate_manual_review_required",
      "warnings": [
        "candidate_only",
        "visual_review_required",
        "not_verified"
      ]
    },
    {
      "candidateId": "ND-2.-Motion-to-Prohibit-Public-Access-AR41-5f1-F005-W01",
      "sourceAcroFormFieldName": "Defendant",
      "fieldType": "text",
      "page": 1,
      "rect": {
        "x": 72,
        "y": 592.2,
        "width": 233.16,
        "height": 14.4
      },
      "draftCanonicalKey": null,
      "canonicalKeyConfidence": "unknown",
      "matcherReason": "No conservative canonical match from AcroForm name or options.",
      "reviewStatus": "manual_review_required",
      "warnings": [
        "candidate_only",
        "visual_review_required",
        "not_verified",
        "manual_mapping_required"
      ]
    },
    {
      "candidateId": "ND-2.-Motion-to-Prohibit-Public-Access-AR41-5f1-F006-W01",
      "sourceAcroFormFieldName": "in the abovenamed",
      "fieldType": "text",
      "page": 1,
      "rect": {
        "x": 135.96,
        "y": 518.88,
        "width": 287.04,
        "height": 14.4
      },
      "draftCanonicalKey": null,
      "canonicalKeyConfidence": "unknown",
      "matcherReason": "No conservative canonical match from AcroForm name or options.",
      "reviewStatus": "manual_review_required",
      "warnings": [
        "candidate_only",
        "visual_review_required",
        "not_verified",
        "manual_mapping_required"
      ]
    },
    {
      "candidateId": "ND-2.-Motion-to-Prohibit-Public-Access-AR41-5f1-F007-W01",
      "sourceAcroFormFieldName": "Telephone Number",
      "fieldType": "text",
      "page": 1,
      "rect": {
        "x": 72,
        "y": 85.2,
        "width": 463.41,
        "height": 19.56
      },
      "draftCanonicalKey": "phone",
      "canonicalKeyConfidence": "medium",
      "matcherReason": "Field name references phone.",
      "reviewStatus": "canonical_key_candidate_manual_review_required",
      "warnings": [
        "candidate_only",
        "visual_review_required",
        "not_verified"
      ]
    },
    {
      "candidateId": "ND-2.-Motion-to-Prohibit-Public-Access-AR41-5f1-F008-W01",
      "sourceAcroFormFieldName": "Check Box1",
      "fieldType": "checkbox",
      "page": 1,
      "rect": {
        "x": 278.02,
        "y": 545.91,
        "width": 18,
        "height": 18
      },
      "draftCanonicalKey": null,
      "canonicalKeyConfidence": "low",
      "matcherReason": "Generic AcroForm name; no verified semantic signal.",
      "reviewStatus": "manual_review_required",
      "warnings": [
        "candidate_only",
        "visual_review_required",
        "not_verified",
        "generic_acroform_name",
        "manual_mapping_required"
      ]
    },
    {
      "candidateId": "ND-2.-Motion-to-Prohibit-Public-Access-AR41-5f1-F009-W01",
      "sourceAcroFormFieldName": "Check Box2",
      "fieldType": "checkbox",
      "page": 1,
      "rect": {
        "x": 336.35,
        "y": 544.86,
        "width": 18,
        "height": 18
      },
      "draftCanonicalKey": null,
      "canonicalKeyConfidence": "low",
      "matcherReason": "Generic AcroForm name; no verified semantic signal.",
      "reviewStatus": "manual_review_required",
      "warnings": [
        "candidate_only",
        "visual_review_required",
        "not_verified",
        "generic_acroform_name",
        "manual_mapping_required"
      ]
    },
    {
      "candidateId": "ND-2.-Motion-to-Prohibit-Public-Access-AR41-5f1-F010-W01",
      "sourceAcroFormFieldName": "Check Box3",
      "fieldType": "checkbox",
      "page": 1,
      "rect": {
        "x": 405.72,
        "y": 544.34,
        "width": 18,
        "height": 18
      },
      "draftCanonicalKey": null,
      "canonicalKeyConfidence": "low",
      "matcherReason": "Generic AcroForm name; no verified semantic signal.",
      "reviewStatus": "manual_review_required",
      "warnings": [
        "candidate_only",
        "visual_review_required",
        "not_verified",
        "generic_acroform_name",
        "manual_mapping_required"
      ]
    },
    {
      "candidateId": "ND-2.-Motion-to-Prohibit-Public-Access-AR41-5f1-F011-W01",
      "sourceAcroFormFieldName": "Check Box4",
      "fieldType": "checkbox",
      "page": 1,
      "rect": {
        "x": 456.18,
        "y": 545.39,
        "width": 18,
        "height": 18
      },
      "draftCanonicalKey": null,
      "canonicalKeyConfidence": "low",
      "matcherReason": "Generic AcroForm name; no verified semantic signal.",
      "reviewStatus": "manual_review_required",
      "warnings": [
        "candidate_only",
        "visual_review_required",
        "not_verified",
        "generic_acroform_name",
        "manual_mapping_required"
      ]
    },
    {
      "candidateId": "ND-2.-Motion-to-Prohibit-Public-Access-AR41-5f1-F012-W01",
      "sourceAcroFormFieldName": "Check Box5",
      "fieldType": "checkbox",
      "page": 1,
      "rect": {
        "x": 474.57,
        "y": 397.71,
        "width": 18,
        "height": 18
      },
      "draftCanonicalKey": null,
      "canonicalKeyConfidence": "low",
      "matcherReason": "Generic AcroForm name; no verified semantic signal.",
      "reviewStatus": "manual_review_required",
      "warnings": [
        "candidate_only",
        "visual_review_required",
        "not_verified",
        "generic_acroform_name",
        "manual_mapping_required"
      ]
    },
    {
      "candidateId": "ND-2.-Motion-to-Prohibit-Public-Access-AR41-5f1-F013-W01",
      "sourceAcroFormFieldName": "Check Box6",
      "fieldType": "checkbox",
      "page": 1,
      "rect": {
        "x": 69.37,
        "y": 368.28,
        "width": 18,
        "height": 18
      },
      "draftCanonicalKey": null,
      "canonicalKeyConfidence": "low",
      "matcherReason": "Generic AcroForm name; no verified semantic signal.",
      "reviewStatus": "manual_review_required",
      "warnings": [
        "candidate_only",
        "visual_review_required",
        "not_verified",
        "generic_acroform_name",
        "manual_mapping_required"
      ]
    },
    {
      "candidateId": "ND-2.-Motion-to-Prohibit-Public-Access-AR41-5f1-F014-W01",
      "sourceAcroFormFieldName": "Printed Name",
      "fieldType": "text",
      "page": 1,
      "rect": {
        "x": 72,
        "y": 155.76,
        "width": 304.92,
        "height": 19.56
      },
      "draftCanonicalKey": "printedName",
      "canonicalKeyConfidence": "high",
      "matcherReason": "Field name is an exact conservative canonical label match.",
      "reviewStatus": "canonical_key_candidate_manual_review_required",
      "warnings": [
        "candidate_only",
        "visual_review_required",
        "not_verified"
      ]
    },
    {
      "candidateId": "ND-2.-Motion-to-Prohibit-Public-Access-AR41-5f1-F015-W01",
      "sourceAcroFormFieldName": "Address",
      "fieldType": "text",
      "page": 1,
      "rect": {
        "x": 72,
        "y": 119.43,
        "width": 463.94,
        "height": 20.61
      },
      "draftCanonicalKey": "address",
      "canonicalKeyConfidence": "high",
      "matcherReason": "Field name is an exact conservative canonical label match.",
      "reviewStatus": "canonical_key_candidate_manual_review_required",
      "warnings": [
        "candidate_only",
        "visual_review_required",
        "not_verified"
      ]
    }
  ]
}
